fastmf/__init__.py
fastmf/generation/__init__.py
fastmf/generation/formatter.py
fastmf/generation/generator.py
fastmf/generation/synthetizer.py
fastmf/inference/__init__.py
fastmf/inference/fullylearned_inference.py
fastmf/inference/hybrid_inference.py
fastmf/models/MLP_FullyLearned.py
fastmf/models/MLP_Split.py
fastmf/models/__init__.py
fastmf/reports/__init__.py
fastmf/reports/evaluator.py
fastmf/utils/NN_utils.py
fastmf/utils/__init__.py
fastmf/utils/mf_estimator.py
fastmf/utils/mf_utils.py
fastmf/utils/tripwire.py
fastmf-0.1.0.dist-info/METADATA
fastmf-0.1.0.dist-info/WHEEL
fastmf-0.1.0.dist-info/RECORD
