Metadata-Version: 2.1
Name: FastMF
Version: 0.1.0
Summary: FastMF is a python package for microstructural property characterization using deep learning based on diffusion MRI data.
Author: Quentin Dessain
Author-email: quentin.dessain@uclouvain.be
Requires-Python: >=3.8,<3.11
Classifier: Programming Language :: Python :: 3
Classifier: Programming Language :: Python :: 3.8
Classifier: Programming Language :: Python :: 3.9
Classifier: Programming Language :: Python :: 3.10
Requires-Dist: cvxpy (<=1.3.1)
Requires-Dist: dipy (>=1.6,<2.0)
Requires-Dist: matplotlib (>=3.5,<4.0)
Requires-Dist: nibabel (<=5.0)
Requires-Dist: numba (<=0.57.0)
Requires-Dist: numpy (>=1.22,<2.0)
Requires-Dist: pathos (<=0.2.8)
Requires-Dist: scikit-learn (<=1.0)
Requires-Dist: scipy (<=1.7.3)
Requires-Dist: torch (<=2.0.0)
Requires-Dist: tqdm (<=4.48)
